LICENSE.txt
MANIFEST.in
README.md
setup.py
tabula/__init__.py
tabula/painter.py
tabula/section.py
tabula/table.py
tabula.egg-info/PKG-INFO
tabula.egg-info/SOURCES.txt
tabula.egg-info/dependency_links.txt
tabula.egg-info/requires.txt
tabula.egg-info/top_level.txt