Metadata-Version: 1.0
Name: tabula
Version: 1.0.2
Summary: Ascii table
Home-page: https://github.com/ronniedada/tabula
Author: Ronnie Sun
Author-email: ronnie@couchbase.com
License: Apache Software License
Keywords: couchbase,terminal,ascii,table,numpy,curses
Platform: UNKNOWN
Classifier: Intended Audience :: Developers
Classifier: Development Status :: 2 - Pre-Alpha
Classifier: Environment :: Console
Classifier: Operating System :: POSIX
Classifier: License :: OSI Approved :: Apache Software License
Classifier: Programming Language :: Python :: 2.6
Classifier: Programming Language :: Python :: 2.7
Classifier: Topic :: Software Development :: Libraries
Classifier: Topic :: Software Development :: User Interfaces
Classifier: Topic :: Terminals
